pyui/__init__.py
pyui/example.py
pyui_org-0.0.1.dist-info/LICENSE
pyui_org-0.0.1.dist-info/METADATA
pyui_org-0.0.1.dist-info/WHEEL
pyui_org-0.0.1.dist-info/top_level.txt
pyui_org-0.0.1.dist-info/RECORD
