Metadata-Version: 2.1
Name: pyui-org
Version: 0.0.1
Summary: Python UI for Web Apps
Author-email: Zain Hoda <zain@pyui.org>
Project-URL: Homepage, https://github.com/pyui-org/pyui
Project-URL: Bug Tracker, https://github.com/pyui-org/pyui/issues
Classifier: Programming Language :: Python :: 3
Classifier: License :: OSI Approved :: MIT License
Classifier: Operating System :: OS Independent
Requires-Python: >=3.7
License-File: LICENSE
